ngd/__init__.py
ngd/programs.py
ngd-0.5.1.dist-info/METADATA
ngd-0.5.1.dist-info/WHEEL
ngd-0.5.1.dist-info/top_level.txt
ngd-0.5.1.dist-info/RECORD
