Metadata-Version: 2.1
Name: ngd
Version: 0.5.1
Summary: A comprehensive programming tutorials package with 25 essential programs
Home-page: https://github.com/yourusername/ngd
Author: Your Name
Author-email: your.email@example.com
Keywords: programming,tutorials,git,flask,docker,kubernetes,jenkins,android,database,web-development,devops
Classifier: Programming Language :: Python :: 3
Classifier: License :: OSI Approved :: MIT License
Classifier: Operating System :: OS Independent
Classifier: Topic :: Software Development :: Libraries :: Python Modules
Classifier: Topic :: Education
Classifier: Development Status :: 4 - Beta
Classifier: Intended Audience :: Developers
Classifier: Intended Audience :: Education
Classifier: Topic :: System :: Systems Administration
Classifier: Topic :: Internet :: WWW/HTTP :: Dynamic Content
Classifier: Topic :: Software Development :: Build Tools
Classifier: Topic :: System :: Networking
Classifier: Topic :: System :: Distributed Computing
Requires-Python: >=3.7
Requires-Dist: flask>=2.0.0
Requires-Dist: requests>=2.25.0
